{
  "saved_ts": "2026-03-04T09:42:23.352317+00:00",
  "endpoint": "/telemetry",
  "payload": {
    "ts": "2026-03-04 12:39:05+00:00",
    "building_id": "RUTGERS-ENG-1",
    "air_node_id": "SIM-001",
    "water_node_id": "WATER-001",
    "air_temp_c": 23.0,
    "air_rh_pct": 97.9,
    "air_surface_temp_c": 20.700000000000003,
    "air_co2_ppm": 636.0,
    "air_pm25_ugm3": null,
    "air_tvoc": null,
    "air_voc_index": 94.0,
    "air_material_moisture": null,
    "water_turbidity_ntu": 0.9,
    "water_tds_ppm": 361.0,
    "water_temp_c": 18.400000000000002,
    "water_free_chlorine_mgL": 1.1500000000000001,
    "scenario": "MOLD_EPISODE",
    "episode_id": "mold_episode_1772617211",
    "data_source": "EMULATED",
    "seq_water": 179,
    "rssi_ble": -63,
    "battery_mv": 3849,
    "flags": 0,
    "site_id": "RUTGERS",
    "building_zone": "ENG-1-BASEMENT",
    "outdoor_temp_c": 8.6,
    "outdoor_rh_pct": 61.900000000000006,
    "outdoor_dew_point_c": 1.0,
    "tod_sin": -0.16934950384902456,
    "tod_cos": -0.9855560590580777,
    "dow_sin": 0.9749279121818236,
    "dow_cos": -0.22252093395631434
  },
  "response": {
    "normalized": {
      "ts": "2026-03-04 12:39:05+00:00",
      "ingest_ts": "2026-03-04 09:42:23.351521+00:00",
      "building_id": "RUTGERS-ENG-1",
      "air_node_id": "SIM-001",
      "water_node_id": "WATER-001",
      "scenario": "MOLD_EPISODE",
      "episode_id": "mold_episode_1772617211",
      "data_source": "EMULATED",
      "seq_water": 179,
      "rssi_ble": -63,
      "battery_mv": 3849,
      "flags": 0,
      "site_id": "RUTGERS",
      "building_zone": "ENG-1-BASEMENT",
      "outdoor_temp_c": 8.6,
      "outdoor_rh_pct": 61.900000000000006,
      "outdoor_dew_point_c": 1.0,
      "tod_sin": -0.16934950384902456,
      "tod_cos": -0.9855560590580777,
      "dow_sin": 0.9749279121818236,
      "dow_cos": -0.22252093395631434,
      "air_temp_c": 23.0,
      "air_rh_pct": 97.9,
      "air_surface_temp_c": 20.700000000000003,
      "air_co2_ppm": 636.0,
      "air_voc_index": 94.0,
      "water_turbidity_ntu": 0.9,
      "water_tds_ppm": 361.0,
      "water_temp_c": 18.400000000000002,
      "water_free_chlorine_mgL": 1.1500000000000001
    },
    "features": {
      "dew_point_c": 22.64959038974983,
      "dew_margin_c": -1.949590389749826,
      "window_s": 300.0,
      "rh_mean_w": 97.85000000000001,
      "rh_std_w": 0.13784048752089953,
      "rh_slope_w": 0.03142857142857005,
      "temp_slope_w": -0.03142857142857157,
      "dew_point_slope_w": -0.026048377702107318,
      "dew_margin_slope_w": -0.01109447944074964,
      "rh_time_above_70_w": 1.0,
      "dew_margin_time_below_0_w": 1.0,
      "air_rh_pct_t_minus_1": 98.0,
      "air_rh_pct_t_minus_5": 97.80000000000001,
      "dew_margin_c_t_minus_5": -1.932464682962852,
      "idx_mold_now_t_minus_5": 0.9928796711700631,
      "idx_mold_now": 0.995605562998509,
      "idx_water_event_now": 0.07445
    },
    "prediction": {
      "target": "idx_mold",
      "horizon_min": 30,
      "yhat": 0.9991443630065175,
      "model_name": "trend_extrap_v1",
      "model_version": "1.0"
    },
    "health": {
      "score": 1.0,
      "warnings": {},
      "data_trust_level": "GOOD"
    },
    "alert_state": {
      "open": true,
      "threshold": 0.8,
      "persistence_n": 3
    },
    "event_times": {
      "pred_cross_ts": "2026-03-04 10:48:05+00:00",
      "pred_resolve_ts": null,
      "actual_cross_ts": "2026-03-04 10:52:05+00:00",
      "actual_resolve_ts": null
    },
    "alert": null,
    "warnings": {}
  }
}